{"jumang4423_1714999346_jumang4423_1714564381": [{"id": "newgarasu", "unfollowed": false, "newly_followed": true, "account_deleted": false}, {"id": "eyes8k", "unfollowed": false, "newly_followed": true, "account_deleted": false}, {"id": "yves_aoi", "unfollowed": false, "newly_followed": true, "account_deleted": false}, {"id": "maji-mengi", "unfollowed": false, "newly_followed": true, "account_deleted": false}, {"id": "ps2lau", "unfollowed": false, "newly_followed": false, "account_deleted": true}, {"id": "candy-prisoner", "unfollowed": false, "newly_followed": false, "account_deleted": true}, {"id": "oila_jp", "unfollowed": true, "newly_followed": false, "account_deleted": false}], "jumang4423_1715094633_jumang4423_1714999346": [{"id": "user-794115220", "unfollowed": false, "newly_followed": true, "account_deleted": false}, {"id": "szazbzxniwvz", "unfollowed": false, "newly_followed": true, "account_deleted": false}, {"id": "user-829492536", "unfollowed": false, "newly_followed": true, "account_deleted": false}], "jumang4423_1715189010_jumang4423_1715094633": [{"id": "yearningwater670", "unfollowed": false, "newly_followed": true, "account_deleted": false}, {"id": "majinchanlugansk", "unfollowed": false, "newly_followed": false, "account_deleted": true}], "jumang4423_1715352933_jumang4423_1715189010": [{"id": "youiddj", "unfollowed": false, "newly_followed": true, "account_deleted": false}], "jumang4423_1715425078_jumang4423_1715352933": [{"id": "jkj-88970666", "unfollowed": false, "newly_followed": true, "account_deleted": false}, {"id": "lucianmoth", "unfollowed": false, "newly_followed": true, "account_deleted": false}], "jumang4423_1715546195_jumang4423_1715425078": [{"id": "shizzooo", "unfollowed": false, "newly_followed": true, "account_deleted": false}, {"id": "56iperr69ybv", "unfollowed": false, "newly_followed": true, "account_deleted": false}, {"id": "rxsljqvycp2r", "unfollowed": false, "newly_followed": true, "account_deleted": false}, {"id": "xhe1ter", "unfollowed": false, "newly_followed": true, "account_deleted": false}, {"id": "unicoroom", "unfollowed": false, "newly_followed": true, "account_deleted": false}, {"id": "ne53", "unfollowed": false, "newly_followed": true, "account_deleted": false}, {"id": "ronald78lol", "unfollowed": true, "newly_followed": false, "account_deleted": false}, {"id": "sadkomusic", "unfollowed": true, "newly_followed": false, "account_deleted": false}], "jumang4423_1715702111_jumang4423_1715546195": [{"id": "marzy_music", "unfollowed": false, "newly_followed": true, "account_deleted": false}, {"id": "x0ri", "unfollowed": false, "newly_followed": true, "account_deleted": false}, {"id": "moffless", "unfollowed": false, "newly_followed": true, "account_deleted": false}, {"id": "haganeyoww", "unfollowed": false, "newly_followed": true, "account_deleted": false}, {"id": "moneyfishhhh", "unfollowed": false, "newly_followed": true, "account_deleted": false}, {"id": "korewayiuko", "unfollowed": false, "newly_followed": true, "account_deleted": false}, {"id": "user-574406838", "unfollowed": false, "newly_followed": false, "account_deleted": true}, {"id": "korewakitti", "unfollowed": false, "newly_followed": false, "account_deleted": true}], "jumang4423_1716041015_jumang4423_1715702111": [{"id": "ezralaeux", "unfollowed": false, "newly_followed": true, "account_deleted": false}, {"id": "hakushi-hasegawa", "unfollowed": false, "newly_followed": true, "account_deleted": false}, {"id": "malikchung", "unfollowed": false, "newly_followed": true, "account_deleted": false}, {"id": "s8a1qiuznozu", "unfollowed": false, "newly_followed": true, "account_deleted": false}, {"id": "tobokegao", "unfollowed": false, "newly_followed": true, "account_deleted": false}, {"id": "aodaruma", "unfollowed": false, "newly_followed": true, "account_deleted": false}, {"id": "ewbkn2kuf4aj", "unfollowed": false, "newly_followed": true, "account_deleted": false}, {"id": "artstate_music", "unfollowed": false, "newly_followed": true, "account_deleted": false}, {"id": "user-891858882", "unfollowed": false, "newly_followed": true, "account_deleted": false}, {"id": "inwikz", "unfollowed": false, "newly_followed": true, "account_deleted": false}, {"id": "amatsuyu", "unfollowed": false, "newly_followed": false, "account_deleted": true}, {"id": "user-623842543", "unfollowed": false, "newly_followed": false, "account_deleted": true}, {"id": "luis-angel-chavez-palma", "unfollowed": true, "newly_followed": false, "account_deleted": false}, {"id": "layingonthefloorwithyou", "unfollowed": false, "newly_followed": false, "account_deleted": true}], "jumang4423_1716127889_jumang4423_1716041015": [{"id": "n4osh1", "unfollowed": false, "newly_followed": true, "account_deleted": false}, {"id": "sinokebanniy", "unfollowed": false, "newly_followed": true, "account_deleted": false}, {"id": "241634794", "unfollowed": false, "newly_followed": true, "account_deleted": false}, {"id": "setsuna2underbar", "unfollowed": false, "newly_followed": true, "account_deleted": false}], "jumang4423_1716224688_jumang4423_1716127889": [{"id": "xaev", "unfollowed": false, "newly_followed": true, "account_deleted": false}, {"id": "rederederede", "unfollowed": false, "newly_followed": true, "account_deleted": false}, {"id": "vanmmusic", "unfollowed": false, "newly_followed": true, "account_deleted": false}, {"id": "deadlysdubz", "unfollowed": false, "newly_followed": true, "account_deleted": false}, {"id": "newtypeboi", "unfollowed": false, "newly_followed": true, "account_deleted": false}, {"id": "p-five-846776751", "unfollowed": false, "newly_followed": true, "account_deleted": false}, {"id": "francky-wallace", "unfollowed": false, "newly_followed": true, "account_deleted": false}, {"id": "u-i-ca", "unfollowed": false, "newly_followed": true, "account_deleted": false}, {"id": "241834794", "unfollowed": false, "newly_followed": true, "account_deleted": false}, {"id": "241634794", "unfollowed": false, "newly_followed": false, "account_deleted": true}], "jumang4423_1716419969_jumang4423_1716224688": [{"id": "color-bass-2", "unfollowed": false, "newly_followed": true, "account_deleted": false}, {"id": "snowydubs", "unfollowed": false, "newly_followed": true, "account_deleted": false}, {"id": "laurondubz", "unfollowed": false, "newly_followed": true, "account_deleted": false}, {"id": "waitingwarmly", "unfollowed": false, "newly_followed": true, "account_deleted": false}, {"id": "decivencesucks", "unfollowed": false, "newly_followed": true, "account_deleted": false}, {"id": "ssoh", "unfollowed": false, "newly_followed": true, "account_deleted": false}, {"id": "theironfist-64420610", "unfollowed": false, "newly_followed": true, "account_deleted": false}, {"id": "fyyann", "unfollowed": false, "newly_followed": true, "account_deleted": false}, {"id": "crx-282847136", "unfollowed": false, "newly_followed": true, "account_deleted": false}, {"id": "yung_ballsack", "unfollowed": false, "newly_followed": true, "account_deleted": false}, {"id": "eyeloveu", "unfollowed": false, "newly_followed": true, "account_deleted": false}, {"id": "nat-000", "unfollowed": false, "newly_followed": true, "account_deleted": false}, {"id": "user9987162", "unfollowed": false, "newly_followed": true, "account_deleted": false}, {"id": "kijuun", "unfollowed": false, "newly_followed": true, "account_deleted": false}, {"id": "nu-514530361", "unfollowed": false, "newly_followed": true, "account_deleted": false}, {"id": "lxgout", "unfollowed": false, "newly_followed": true, "account_deleted": false}, {"id": "lainmp3", "unfollowed": false, "newly_followed": true, "account_deleted": false}, {"id": "yushiro_0124", "unfollowed": false, "newly_followed": true, "account_deleted": false}, {"id": "francky-wallace", "unfollowed": false, "newly_followed": false, "account_deleted": true}, {"id": "241834794", "unfollowed": false, "newly_followed": false, "account_deleted": true}, {"id": "h4rddriv3", "unfollowed": true, "newly_followed": false, "account_deleted": false}, {"id": "harmonex", "unfollowed": false, "newly_followed": false, "account_deleted": true}, {"id": "yushiro_1", "unfollowed": false, "newly_followed": false, "account_deleted": true}], "jumang4423_1716709961_jumang4423_1716419969": [{"id": "user-766391661", "unfollowed": false, "newly_followed": true, "account_deleted": false}, {"id": "brokemun", "unfollowed": false, "newly_followed": true, "account_deleted": false}, {"id": "noen2006", "unfollowed": false, "newly_followed": true, "account_deleted": false}, {"id": "heavensdoorservice", "unfollowed": false, "newly_followed": true, "account_deleted": false}, {"id": "digitalreject", "unfollowed": false, "newly_followed": true, "account_deleted": false}, {"id": "user-213201088", "unfollowed": false, "newly_followed": true, "account_deleted": false}, {"id": "non-256707795", "unfollowed": false, "newly_followed": true, "account_deleted": false}, {"id": "jack-davenport-889646669", "unfollowed": false, "newly_followed": true, "account_deleted": false}, {"id": "friend-110010855", "unfollowed": false, "newly_followed": true, "account_deleted": false}, {"id": "amalgirlmation", "unfollowed": false, "newly_followed": true, "account_deleted": false}, {"id": "men2you", "unfollowed": false, "newly_followed": true, "account_deleted": false}, {"id": "vaeins19", "unfollowed": false, "newly_followed": true, "account_deleted": false}, {"id": "lvx70rbee3br", "unfollowed": true, "newly_followed": false, "account_deleted": false}, {"id": "vaeins-is-malay", "unfollowed": false, "newly_followed": false, "account_deleted": true}], "jumang4423_1716710134_jumang4423_1716709961": [], "jumang4423_1716710134_jumang4423_1716419969": [{"id": "user-766391661", "unfollowed": false, "newly_followed": true, "account_deleted": false}, {"id": "brokemun", "unfollowed": false, "newly_followed": true, "account_deleted": false}, {"id": "noen2006", "unfollowed": false, "newly_followed": true, "account_deleted": false}, {"id": "heavensdoorservice", "unfollowed": false, "newly_followed": true, "account_deleted": false}, {"id": "digitalreject", "unfollowed": false, "newly_followed": true, "account_deleted": false}, {"id": "user-213201088", "unfollowed": false, "newly_followed": true, "account_deleted": false}, {"id": "non-256707795", "unfollowed": false, "newly_followed": true, "account_deleted": false}, {"id": "jack-davenport-889646669", "unfollowed": false, "newly_followed": true, "account_deleted": false}, {"id": "friend-110010855", "unfollowed": false, "newly_followed": true, "account_deleted": false}, {"id": "amalgirlmation", "unfollowed": false, "newly_followed": true, "account_deleted": false}, {"id": "men2you", "unfollowed": false, "newly_followed": true, "account_deleted": false}, {"id": "vaeins19", "unfollowed": false, "newly_followed": true, "account_deleted": false}, {"id": "lvx70rbee3br", "unfollowed": true, "newly_followed": false, "account_deleted": false}, {"id": "vaeins-is-malay", "unfollowed": false, "newly_followed": false, "account_deleted": true}], "jumang4423_1717054789_jumang4423_1716710134": [{"id": "blujay-music", "unfollowed": false, "newly_followed": true, "account_deleted": false}, {"id": "81zaki", "unfollowed": false, "newly_followed": true, "account_deleted": false}, {"id": "fadedskymusic", "unfollowed": false, "newly_followed": true, "account_deleted": false}, {"id": "waffleheads", "unfollowed": false, "newly_followed": true, "account_deleted": false}, {"id": "frogchaser", "unfollowed": false, "newly_followed": true, "account_deleted": false}, {"id": "get_crazy-609153271", "unfollowed": false, "newly_followed": true, "account_deleted": false}, {"id": "saintcaribou", "unfollowed": false, "newly_followed": true, "account_deleted": false}, {"id": "vuvuvuvu", "unfollowed": false, "newly_followed": true, "account_deleted": false}, {"id": "sloevibes", "unfollowed": false, "newly_followed": true, "account_deleted": false}, {"id": "f1j2t8sdzskl", "unfollowed": false, "newly_followed": true, "account_deleted": false}, {"id": "dj_surveillance", "unfollowed": false, "newly_followed": true, "account_deleted": false}, {"id": "goo_2", "unfollowed": false, "newly_followed": true, "account_deleted": false}, {"id": "nassim00", "unfollowed": false, "newly_followed": true, "account_deleted": false}, {"id": "infinity_musique", "unfollowed": false, "newly_followed": true, "account_deleted": false}, {"id": "nyan-chu-666", "unfollowed": false, "newly_followed": false, "account_deleted": true}, {"id": "horridd", "unfollowed": true, "newly_followed": false, "account_deleted": false}, {"id": "goo_age", "unfollowed": false, "newly_followed": false, "account_deleted": true}, {"id": "nassim453", "unfollowed": false, "newly_followed": false, "account_deleted": true}, {"id": "infinity-musique", "unfollowed": false, "newly_followed": false, "account_deleted": true}, {"id": "horems", "unfollowed": false, "newly_followed": false, "account_deleted": true}], "jumang4423_1717250102_jumang4423_1717054789": [{"id": "user-962106302", "unfollowed": false, "newly_followed": true, "account_deleted": false}, {"id": "losknx", "unfollowed": false, "newly_followed": true, "account_deleted": false}, {"id": "karisawa3", "unfollowed": false, "newly_followed": true, "account_deleted": false}, {"id": "zaconline", "unfollowed": false, "newly_followed": true, "account_deleted": false}, {"id": "z_o_r_k", "unfollowed": false, "newly_followed": false, "account_deleted": true}, {"id": "user-175376874", "unfollowed": true, "newly_followed": false, "account_deleted": false}, {"id": "404-e", "unfollowed": true, "newly_followed": false, "account_deleted": false}], "jumang4423_1717484639_jumang4423_1717250102": [{"id": "addison-baum-39430351", "unfollowed": false, "newly_followed": true, "account_deleted": false}, {"id": "enablesecret", "unfollowed": false, "newly_followed": true, "account_deleted": false}, {"id": "maddie-damp", "unfollowed": false, "newly_followed": true, "account_deleted": false}, {"id": "d9eyotrjuotl", "unfollowed": false, "newly_followed": true, "account_deleted": false}, {"id": "plaieboi", "unfollowed": false, "newly_followed": true, "account_deleted": false}, {"id": "cyb1l_0", "unfollowed": false, "newly_followed": true, "account_deleted": false}, {"id": "aphextwinsucks", "unfollowed": false, "newly_followed": true, "account_deleted": false}, {"id": "satellite-686722453", "unfollowed": false, "newly_followed": true, "account_deleted": false}, {"id": "dotb5201", "unfollowed": false, "newly_followed": true, "account_deleted": false}, {"id": "istilldonthavefriends", "unfollowed": false, "newly_followed": true, "account_deleted": false}, {"id": "daisuke4230", "unfollowed": false, "newly_followed": false, "account_deleted": true}, {"id": "benoomf", "unfollowed": false, "newly_followed": false, "account_deleted": true}, {"id": "skinny2b", "unfollowed": false, "newly_followed": false, "account_deleted": true}], "jumang4423_1718296410_jumang4423_1717484639": [{"id": "moodnightmusic", "unfollowed": false, "newly_followed": true, "account_deleted": false}, {"id": "xehlehpdrfio", "unfollowed": false, "newly_followed": true, "account_deleted": false}, {"id": "namigroove", "unfollowed": false, "newly_followed": true, "account_deleted": false}, {"id": "notpure0", "unfollowed": false, "newly_followed": true, "account_deleted": false}, {"id": "1roseara", "unfollowed": false, "newly_followed": true, "account_deleted": false}, {"id": "kensley-fuqua-32815164", "unfollowed": false, "newly_followed": true, "account_deleted": false}, {"id": "ktoooyaa", "unfollowed": false, "newly_followed": true, "account_deleted": false}, {"id": "hhvpa5e7vr3h", "unfollowed": false, "newly_followed": true, "account_deleted": false}, {"id": "jonathan-kok-wai-ho", "unfollowed": false, "newly_followed": true, "account_deleted": false}, {"id": "guessglass", "unfollowed": false, "newly_followed": true, "account_deleted": false}, {"id": "2711592504", "unfollowed": false, "newly_followed": true, "account_deleted": false}, {"id": "djfrogattack", "unfollowed": false, "newly_followed": true, "account_deleted": false}, {"id": "1plush", "unfollowed": false, "newly_followed": true, "account_deleted": false}, {"id": "98465475", "unfollowed": false, "newly_followed": true, "account_deleted": false}, {"id": "thoroughlyrelaxed", "unfollowed": false, "newly_followed": true, "account_deleted": false}, {"id": "caokram", "unfollowed": false, "newly_followed": true, "account_deleted": false}, {"id": "plushxwx", "unfollowed": false, "newly_followed": false, "account_deleted": true}, {"id": "jtchapman01", "unfollowed": false, "newly_followed": false, "account_deleted": true}, {"id": "dj_surveillance", "unfollowed": true, "newly_followed": false, "account_deleted": false}, {"id": "coloringpencils", "unfollowed": false, "newly_followed": false, "account_deleted": true}, {"id": "creepykat9", "unfollowed": false, "newly_followed": false, "account_deleted": true}, {"id": "nghugh", "unfollowed": true, "newly_followed": false, "account_deleted": false}, {"id": "cokram", "unfollowed": true, "newly_followed": false, "account_deleted": false}], "jumang4423_1718642973_jumang4423_1718296410": [{"id": "kairuidesu", "unfollowed": false, "newly_followed": true, "account_deleted": false}, {"id": "user-967846970", "unfollowed": false, "newly_followed": true, "account_deleted": false}, {"id": "bishnu-saikia-16373696", "unfollowed": false, "newly_followed": true, "account_deleted": false}, {"id": "naw-cho-cho-lwin", "unfollowed": false, "newly_followed": true, "account_deleted": false}, {"id": "egoseed", "unfollowed": false, "newly_followed": true, "account_deleted": false}, {"id": "juseva", "unfollowed": false, "newly_followed": true, "account_deleted": false}, {"id": "frog96", "unfollowed": false, "newly_followed": true, "account_deleted": false}, {"id": "pluggbient", "unfollowed": false, "newly_followed": true, "account_deleted": false}, {"id": "lauron_prd", "unfollowed": false, "newly_followed": true, "account_deleted": false}, {"id": "2711592504", "unfollowed": false, "newly_followed": false, "account_deleted": true}, {"id": "laurondubz", "unfollowed": false, "newly_followed": false, "account_deleted": true}], "zamesu_1718643597_zamesu_1718202552": [{"id": "6hwdn5rsvg27", "unfollowed": false, "newly_followed": true, "account_deleted": false}, {"id": "user-715038316", "unfollowed": false, "newly_followed": true, "account_deleted": false}, {"id": "w6ipjpxqfadu", "unfollowed": false, "newly_followed": true, "account_deleted": false}, {"id": "desmond-cayce", "unfollowed": false, "newly_followed": true, "account_deleted": false}, {"id": "nguyen-foxeiz", "unfollowed": false, "newly_followed": true, "account_deleted": false}, {"id": "xehlehpdrfio", "unfollowed": false, "newly_followed": true, "account_deleted": false}, {"id": "la_kuroparfait", "unfollowed": false, "newly_followed": true, "account_deleted": false}, {"id": "chihiro-in-the-sky", "unfollowed": false, "newly_followed": true, "account_deleted": false}, {"id": "light-action", "unfollowed": false, "newly_followed": false, "account_deleted": true}, {"id": "alex-blyon", "unfollowed": false, "newly_followed": false, "account_deleted": true}], "jumang4423_1719339692_jumang4423_1718642973": [{"id": "pio-music-421132766", "unfollowed": false, "newly_followed": true, "account_deleted": false}, {"id": "user110100111011001111001", "unfollowed": false, "newly_followed": true, "account_deleted": false}, {"id": "pswjt", "unfollowed": false, "newly_followed": true, "account_deleted": false}, {"id": "adrian-gonzalez-78", "unfollowed": false, "newly_followed": true, "account_deleted": false}, {"id": "righteous-989064382", "unfollowed": false, "newly_followed": true, "account_deleted": false}, {"id": "neuume", "unfollowed": false, "newly_followed": true, "account_deleted": false}, {"id": "vintmint", "unfollowed": false, "newly_followed": true, "account_deleted": false}, {"id": "vikksen", "unfollowed": false, "newly_followed": true, "account_deleted": false}, {"id": "user-623411900", "unfollowed": false, "newly_followed": true, "account_deleted": false}, {"id": "umeaeixgvvvf", "unfollowed": false, "newly_followed": true, "account_deleted": false}, {"id": "hypnotherapy444", "unfollowed": false, "newly_followed": true, "account_deleted": false}, {"id": "maezawa-lab", "unfollowed": false, "newly_followed": true, "account_deleted": false}, {"id": "djsquirrel4", "unfollowed": false, "newly_followed": true, "account_deleted": false}, {"id": "getfrommyaccountbitch", "unfollowed": false, "newly_followed": true, "account_deleted": false}, {"id": "kodomonie", "unfollowed": false, "newly_followed": true, "account_deleted": false}, {"id": "benoomf", "unfollowed": false, "newly_followed": true, "account_deleted": false}, {"id": "eph_kni", "unfollowed": false, "newly_followed": true, "account_deleted": false}, {"id": "n0ky4", "unfollowed": false, "newly_followed": true, "account_deleted": false}, {"id": "digitalsvlt", "unfollowed": false, "newly_followed": true, "account_deleted": false}, {"id": "submissivesquirrel", "unfollowed": true, "newly_followed": false, "account_deleted": false}, {"id": "vaeins19", "unfollowed": false, "newly_followed": false, "account_deleted": true}, {"id": "moufuu", "unfollowed": false, "newly_followed": false, "account_deleted": true}, {"id": "dotb5201", "unfollowed": false, "newly_followed": false, "account_deleted": true}, {"id": "joykon", "unfollowed": false, "newly_followed": false, "account_deleted": true}, {"id": "gustavolegal", "unfollowed": false, "newly_followed": false, "account_deleted": true}, {"id": "kyxjx", "unfollowed": false, "newly_followed": false, "account_deleted": true}], "jumang4423_1720711096_jumang4423_1719339692": [{"id": "lol-auieo", "unfollowed": false, "newly_followed": true, "account_deleted": false}, {"id": "idk09999", "unfollowed": false, "newly_followed": true, "account_deleted": false}, {"id": "samshiana", "unfollowed": false, "newly_followed": true, "account_deleted": false}, {"id": "nanodesuarli", "unfollowed": false, "newly_followed": true, "account_deleted": false}, {"id": "oddyssi", "unfollowed": false, "newly_followed": true, "account_deleted": false}, {"id": "arcticnoah", "unfollowed": false, "newly_followed": true, "account_deleted": false}, {"id": "zqldvgovib7e", "unfollowed": false, "newly_followed": true, "account_deleted": false}, {"id": "4toku", "unfollowed": false, "newly_followed": true, "account_deleted": false}, {"id": "okinyan", "unfollowed": false, "newly_followed": true, "account_deleted": false}, {"id": "linkedwinters", "unfollowed": false, "newly_followed": true, "account_deleted": false}, {"id": "mi_so_ka", "unfollowed": false, "newly_followed": true, "account_deleted": false}, {"id": "user-938175878", "unfollowed": false, "newly_followed": true, "account_deleted": false}, {"id": "luvparadeee", "unfollowed": false, "newly_followed": true, "account_deleted": false}, {"id": "mr-shochan", "unfollowed": false, "newly_followed": true, "account_deleted": false}, {"id": "yungwaveydave", "unfollowed": false, "newly_followed": true, "account_deleted": false}, {"id": "christian-536430807", "unfollowed": false, "newly_followed": true, "account_deleted": false}, {"id": "s-ko-402470742", "unfollowed": false, "newly_followed": true, "account_deleted": false}, {"id": "uniwalier", "unfollowed": false, "newly_followed": true, "account_deleted": false}, {"id": "2mmmmm", "unfollowed": false, "newly_followed": true, "account_deleted": false}, {"id": "risorah", "unfollowed": false, "newly_followed": true, "account_deleted": false}, {"id": "0verdie", "unfollowed": false, "newly_followed": true, "account_deleted": false}, {"id": "nesodude", "unfollowed": false, "newly_followed": true, "account_deleted": false}, {"id": "daguisongpu7", "unfollowed": false, "newly_followed": true, "account_deleted": false}, {"id": "solvaki", "unfollowed": false, "newly_followed": true, "account_deleted": false}, {"id": "moesabetsu", "unfollowed": false, "newly_followed": true, "account_deleted": false}, {"id": "binnykilla", "unfollowed": false, "newly_followed": true, "account_deleted": false}, {"id": "color-bass-2-ids", "unfollowed": false, "newly_followed": true, "account_deleted": false}, {"id": "howibeenfeeling", "unfollowed": false, "newly_followed": true, "account_deleted": false}, {"id": "kuzzcoo", "unfollowed": false, "newly_followed": true, "account_deleted": false}, {"id": "fmroe135", "unfollowed": false, "newly_followed": true, "account_deleted": false}, {"id": "dotbrkr", "unfollowed": false, "newly_followed": true, "account_deleted": false}, {"id": "3sky3", "unfollowed": false, "newly_followed": true, "account_deleted": false}, {"id": "mossgarden1", "unfollowed": false, "newly_followed": true, "account_deleted": false}, {"id": "infinityquency", "unfollowed": false, "newly_followed": true, "account_deleted": false}, {"id": "ecromusic", "unfollowed": false, "newly_followed": true, "account_deleted": false}, {"id": "windwardmusic", "unfollowed": false, "newly_followed": true, "account_deleted": false}, {"id": "mitamatunes", "unfollowed": false, "newly_followed": true, "account_deleted": false}, {"id": "juseva", "unfollowed": true, "newly_followed": false, "account_deleted": false}, {"id": "color-bass-2", "unfollowed": false, "newly_followed": false, "account_deleted": true}, {"id": "xaev", "unfollowed": true, "newly_followed": false, "account_deleted": false}, {"id": "iloveallmydogs", "unfollowed": false, "newly_followed": false, "account_deleted": true}, {"id": "kuzzcooo", "unfollowed": false, "newly_followed": false, "account_deleted": true}, {"id": "sdmfjsatrnrovwea", "unfollowed": false, "newly_followed": false, "account_deleted": true}, {"id": "marinesong2001", "unfollowed": false, "newly_followed": false, "account_deleted": true}, {"id": "benoomf", "unfollowed": false, "newly_followed": false, "account_deleted": true}, {"id": "learningtorelax", "unfollowed": false, "newly_followed": false, "account_deleted": true}, {"id": "ollies-music", "unfollowed": false, "newly_followed": false, "account_deleted": true}, {"id": "lalanoi", "unfollowed": true, "newly_followed": false, "account_deleted": false}, {"id": "mossgardenn", "unfollowed": true, "newly_followed": false, "account_deleted": false}, {"id": "infinity_musique", "unfollowed": false, "newly_followed": false, "account_deleted": true}, {"id": "skyltraxx", "unfollowed": false, "newly_followed": false, "account_deleted": true}, {"id": "windwardvr", "unfollowed": false, "newly_followed": false, "account_deleted": true}, {"id": "ntrsound", "unfollowed": false, "newly_followed": false, "account_deleted": true}, {"id": "nabil_aiman", "unfollowed": true, "newly_followed": false, "account_deleted": false}], "jumang4423_1721270065_jumang4423_1720711096": [{"id": "sashalex-gg", "unfollowed": false, "newly_followed": true, "account_deleted": false}, {"id": "cheza27", "unfollowed": false, "newly_followed": true, "account_deleted": false}, {"id": "klu3", "unfollowed": false, "newly_followed": true, "account_deleted": false}, {"id": "novander1", "unfollowed": false, "newly_followed": true, "account_deleted": false}, {"id": "officialnoctane", "unfollowed": false, "newly_followed": true, "account_deleted": false}, {"id": "kousaka_san", "unfollowed": false, "newly_followed": true, "account_deleted": false}, {"id": "viani-destello", "unfollowed": false, "newly_followed": true, "account_deleted": false}, {"id": "iw6x", "unfollowed": false, "newly_followed": true, "account_deleted": false}, {"id": "lolaiueo", "unfollowed": false, "newly_followed": true, "account_deleted": false}, {"id": "lol-auieo", "unfollowed": false, "newly_followed": false, "account_deleted": true}, {"id": "pluggbient", "unfollowed": false, "newly_followed": false, "account_deleted": true}, {"id": "llznia", "unfollowed": true, "newly_followed": false, "account_deleted": false}], "jumang4423_1721394803_jumang4423_1721270065": [{"id": "euchmad", "unfollowed": false, "newly_followed": true, "account_deleted": false}, {"id": "rgbattack", "unfollowed": false, "newly_followed": true, "account_deleted": false}, {"id": "tailspun", "unfollowed": false, "newly_followed": true, "account_deleted": false}, {"id": "virtualambience", "unfollowed": false, "newly_followed": true, "account_deleted": false}, {"id": "hypnotherapy444", "unfollowed": false, "newly_followed": false, "account_deleted": true}, {"id": "addison-baum-39430351", "unfollowed": false, "newly_followed": false, "account_deleted": true}, {"id": "stardew", "unfollowed": false, "newly_followed": false, "account_deleted": true}, {"id": "kosuke-nishiyama", "unfollowed": false, "newly_followed": false, "account_deleted": true}], "jumang4423_1721744101_jumang4423_1721394803": [{"id": "cerubble3838", "unfollowed": false, "newly_followed": true, "account_deleted": false}, {"id": "nirfumzzlf7o", "unfollowed": false, "newly_followed": true, "account_deleted": false}, {"id": "smith-jane-943876654", "unfollowed": false, "newly_followed": true, "account_deleted": false}, {"id": "kouodbefztgu", "unfollowed": false, "newly_followed": true, "account_deleted": false}, {"id": "tangenttheta", "unfollowed": false, "newly_followed": true, "account_deleted": false}, {"id": "5xq", "unfollowed": false, "newly_followed": true, "account_deleted": false}, {"id": "evilestpetshop", "unfollowed": false, "newly_followed": true, "account_deleted": false}, {"id": "1mint", "unfollowed": false, "newly_followed": true, "account_deleted": false}, {"id": "chris-osorio-732687144", "unfollowed": false, "newly_followed": true, "account_deleted": false}, {"id": "popbot1", "unfollowed": false, "newly_followed": true, "account_deleted": false}, {"id": "hypnotherapy444", "unfollowed": false, "newly_followed": true, "account_deleted": false}, {"id": "concerninggggg", "unfollowed": false, "newly_followed": true, "account_deleted": false}, {"id": "vvvincenttt", "unfollowed": false, "newly_followed": false, "account_deleted": true}], "jumang4423_1722085921_jumang4423_1721744101": [{"id": "lxghtend", "unfollowed": false, "newly_followed": true, "account_deleted": false}, {"id": "dz90gfdvdrhy", "unfollowed": false, "newly_followed": true, "account_deleted": false}, {"id": "masha9192", "unfollowed": false, "newly_followed": true, "account_deleted": false}, {"id": "dedsillying2928", "unfollowed": false, "newly_followed": true, "account_deleted": false}, {"id": "merilynn_very_cool", "unfollowed": false, "newly_followed": true, "account_deleted": false}, {"id": "iloveallmydogs", "unfollowed": false, "newly_followed": true, "account_deleted": false}, {"id": "dotbreaker", "unfollowed": false, "newly_followed": true, "account_deleted": false}, {"id": "howibeenfeeling", "unfollowed": true, "newly_followed": false, "account_deleted": false}, {"id": "dotbrkr", "unfollowed": false, "newly_followed": false, "account_deleted": true}, {"id": "voysol", "unfollowed": false, "newly_followed": false, "account_deleted": true}], "jumang4423_1722292039_jumang4423_1722085921": [{"id": "kinu_nu390", "unfollowed": false, "newly_followed": true, "account_deleted": false}, {"id": "stysan", "unfollowed": false, "newly_followed": true, "account_deleted": false}, {"id": "leesick", "unfollowed": false, "newly_followed": true, "account_deleted": false}, {"id": "y00puriprism", "unfollowed": false, "newly_followed": true, "account_deleted": false}, {"id": "sagara_nao", "unfollowed": true, "newly_followed": false, "account_deleted": false}, {"id": "stisan", "unfollowed": false, "newly_followed": false, "account_deleted": true}, {"id": "gl4cier", "unfollowed": false, "newly_followed": false, "account_deleted": true}, {"id": "alterprismic", "unfollowed": false, "newly_followed": false, "account_deleted": true}, {"id": "amebient", "unfollowed": false, "newly_followed": false, "account_deleted": true}, {"id": "netnegativity", "unfollowed": true, "newly_followed": false, "account_deleted": false}], "jumang4423_1722348581_jumang4423_1722292039": [{"id": "seakidmollusk", "unfollowed": false, "newly_followed": true, "account_deleted": false}, {"id": "4toku", "unfollowed": true, "newly_followed": false, "account_deleted": false}, {"id": "nicekaylee", "unfollowed": false, "newly_followed": false, "account_deleted": true}], "jumang4423_1722535229_jumang4423_1722348581": [{"id": "4toku", "unfollowed": false, "newly_followed": true, "account_deleted": false}, {"id": "alicciaaa", "unfollowed": false, "newly_followed": true, "account_deleted": false}, {"id": "hyug0u", "unfollowed": false, "newly_followed": true, "account_deleted": false}, {"id": "camillamillz", "unfollowed": false, "newly_followed": true, "account_deleted": false}, {"id": "mkl_millz", "unfollowed": false, "newly_followed": false, "account_deleted": true}], "jumang4423_1722942029_jumang4423_1722535229": [{"id": "le_papa_dei", "unfollowed": false, "newly_followed": true, "account_deleted": false}, {"id": "sorrythug", "unfollowed": false, "newly_followed": true, "account_deleted": false}, {"id": "thejapanchannel1986", "unfollowed": false, "newly_followed": true, "account_deleted": false}, {"id": "patricia-n-ez-3", "unfollowed": false, "newly_followed": true, "account_deleted": false}, {"id": "raindubz", "unfollowed": false, "newly_followed": true, "account_deleted": false}, {"id": "notrain", "unfollowed": false, "newly_followed": false, "account_deleted": true}], "jumang4423_1725969113_jumang4423_1722942029": [{"id": "whyawe", "unfollowed": false, "newly_followed": true, "account_deleted": false}, {"id": "akari_313k", "unfollowed": false, "newly_followed": true, "account_deleted": false}, {"id": "exhiledub", "unfollowed": false, "newly_followed": true, "account_deleted": false}, {"id": "mafia-liminal", "unfollowed": false, "newly_followed": true, "account_deleted": false}, {"id": "user-433648598", "unfollowed": false, "newly_followed": true, "account_deleted": false}, {"id": "seoulmina", "unfollowed": false, "newly_followed": true, "account_deleted": false}, {"id": "plsdonate333", "unfollowed": false, "newly_followed": true, "account_deleted": false}, {"id": "s6wkzuyopzcv", "unfollowed": false, "newly_followed": true, "account_deleted": false}, {"id": "tgwog", "unfollowed": false, "newly_followed": true, "account_deleted": false}, {"id": "aa-a-41512808", "unfollowed": false, "newly_followed": true, "account_deleted": false}, {"id": "yzsi", "unfollowed": false, "newly_followed": true, "account_deleted": false}, {"id": "yerin0821yerin", "unfollowed": false, "newly_followed": true, "account_deleted": false}, {"id": "guinneissik00", "unfollowed": false, "newly_followed": true, "account_deleted": false}, {"id": "mendako", "unfollowed": false, "newly_followed": true, "account_deleted": false}, {"id": "zixsszixss", "unfollowed": false, "newly_followed": true, "account_deleted": false}, {"id": "qlxupwbaj1dm", "unfollowed": false, "newly_followed": true, "account_deleted": false}, {"id": "neon-sound-wave-music", "unfollowed": false, "newly_followed": true, "account_deleted": false}, {"id": "user-530058012", "unfollowed": false, "newly_followed": true, "account_deleted": false}, {"id": "thomasvoj", "unfollowed": false, "newly_followed": true, "account_deleted": false}, {"id": "user-129559677-532916749", "unfollowed": false, "newly_followed": true, "account_deleted": false}, {"id": "winipu", "unfollowed": false, "newly_followed": true, "account_deleted": false}, {"id": "user-231805458", "unfollowed": false, "newly_followed": true, "account_deleted": false}, {"id": "ruqcie-4u", "unfollowed": false, "newly_followed": true, "account_deleted": false}, {"id": "lightwired", "unfollowed": false, "newly_followed": true, "account_deleted": false}, {"id": "rsrz3jxx8tsw", "unfollowed": false, "newly_followed": true, "account_deleted": false}, {"id": "045-hibiki", "unfollowed": false, "newly_followed": true, "account_deleted": false}, {"id": "nuphory", "unfollowed": false, "newly_followed": true, "account_deleted": false}, {"id": "user-802728012", "unfollowed": false, "newly_followed": true, "account_deleted": false}, {"id": "user-330058400", "unfollowed": false, "newly_followed": true, "account_deleted": false}, {"id": "tshorts", "unfollowed": false, "newly_followed": true, "account_deleted": false}, {"id": "nameo-137862090", "unfollowed": false, "newly_followed": true, "account_deleted": false}, {"id": "user-711933822", "unfollowed": false, "newly_followed": true, "account_deleted": false}, {"id": "tuyofumi", "unfollowed": false, "newly_followed": true, "account_deleted": false}, {"id": "powwwerpoint", "unfollowed": false, "newly_followed": true, "account_deleted": false}, {"id": "dekalog1", "unfollowed": false, "newly_followed": true, "account_deleted": false}, {"id": "michelle-pan-18395442", "unfollowed": false, "newly_followed": true, "account_deleted": false}, {"id": "user-520493006", "unfollowed": false, "newly_followed": true, "account_deleted": false}, {"id": "sisi3882", "unfollowed": false, "newly_followed": true, "account_deleted": false}, {"id": "shrxnii8dwxm", "unfollowed": false, "newly_followed": true, "account_deleted": false}, {"id": "madoxy", "unfollowed": false, "newly_followed": true, "account_deleted": false}, {"id": "2016_1119", "unfollowed": false, "newly_followed": true, "account_deleted": false}, {"id": "kikokusi", "unfollowed": false, "newly_followed": true, "account_deleted": false}, {"id": "9kqes4zpmzq9", "unfollowed": false, "newly_followed": true, "account_deleted": false}, {"id": "soilx_0abc", "unfollowed": false, "newly_followed": true, "account_deleted": false}, {"id": "user-14062235", "unfollowed": false, "newly_followed": true, "account_deleted": false}, {"id": "vanfleet", "unfollowed": false, "newly_followed": true, "account_deleted": false}, {"id": "k-e-n-a-iiiiiiii", "unfollowed": false, "newly_followed": true, "account_deleted": false}, {"id": "destiny-ogbeide", "unfollowed": false, "newly_followed": true, "account_deleted": false}, {"id": "lovfully", "unfollowed": false, "newly_followed": true, "account_deleted": false}, {"id": "misousoup", "unfollowed": false, "newly_followed": true, "account_deleted": false}, {"id": "user-623842543", "unfollowed": false, "newly_followed": true, "account_deleted": false}, {"id": "itz_shy", "unfollowed": false, "newly_followed": true, "account_deleted": false}, {"id": "vaenis25", "unfollowed": false, "newly_followed": true, "account_deleted": false}, {"id": "yunokai_dtm", "unfollowed": false, "newly_followed": true, "account_deleted": false}, {"id": "svlky", "unfollowed": false, "newly_followed": true, "account_deleted": false}, {"id": "b5201", "unfollowed": false, "newly_followed": true, "account_deleted": false}, {"id": "karoocaloo", "unfollowed": false, "newly_followed": true, "account_deleted": false}, {"id": "protocolseven", "unfollowed": false, "newly_followed": true, "account_deleted": false}, {"id": "clinique9", "unfollowed": false, "newly_followed": true, "account_deleted": false}, {"id": "fs47", "unfollowed": false, "newly_followed": true, "account_deleted": false}, {"id": "deadatchristmas", "unfollowed": false, "newly_followed": true, "account_deleted": false}, {"id": "sagesagesagesagesage", "unfollowed": false, "newly_followed": true, "account_deleted": false}, {"id": "daxhuntlover", "unfollowed": false, "newly_followed": true, "account_deleted": false}, {"id": "mycatlarry", "unfollowed": false, "newly_followed": true, "account_deleted": false}, {"id": "lunarland", "unfollowed": false, "newly_followed": true, "account_deleted": false}, {"id": "4toku", "unfollowed": true, "newly_followed": false, "account_deleted": false}, {"id": "n4osh1", "unfollowed": true, "newly_followed": false, "account_deleted": false}, {"id": "yaayyy", "unfollowed": false, "newly_followed": false, "account_deleted": true}, {"id": "loliwise", "unfollowed": false, "newly_followed": false, "account_deleted": true}, {"id": "touyacametoplay", "unfollowed": false, "newly_followed": false, "account_deleted": true}, {"id": "hojk5umal7ut", "unfollowed": false, "newly_followed": false, "account_deleted": true}, {"id": "getfrommyaccountbitch", "unfollowed": false, "newly_followed": false, "account_deleted": true}, {"id": "yunokaidesu", "unfollowed": false, "newly_followed": false, "account_deleted": true}, {"id": "user-537891242", "unfollowed": false, "newly_followed": false, "account_deleted": true}, {"id": "dotbreaker", "unfollowed": false, "newly_followed": false, "account_deleted": true}, {"id": "kangaroocaloo", "unfollowed": false, "newly_followed": false, "account_deleted": true}, {"id": "prodglitchless", "unfollowed": false, "newly_followed": false, "account_deleted": true}, {"id": "gale-988682456", "unfollowed": false, "newly_followed": false, "account_deleted": true}, {"id": "y00puriprism", "unfollowed": false, "newly_followed": false, "account_deleted": true}, {"id": "istilldonthavefriends", "unfollowed": false, "newly_followed": false, "account_deleted": true}, {"id": "breakchildaltuwu", "unfollowed": false, "newly_followed": false, "account_deleted": true}, {"id": "shoochuu", "unfollowed": false, "newly_followed": false, "account_deleted": true}, {"id": "mitei_music", "unfollowed": true, "newly_followed": false, "account_deleted": false}, {"id": "oatmilkmf", "unfollowed": false, "newly_followed": false, "account_deleted": true}, {"id": "airainfo", "unfollowed": false, "newly_followed": false, "account_deleted": true}], "jumang4423_1726146160_jumang4423_1725969113": [{"id": "frenitian", "unfollowed": false, "newly_followed": true, "account_deleted": false}, {"id": "color-inc", "unfollowed": false, "newly_followed": true, "account_deleted": false}, {"id": "pluggbient", "unfollowed": false, "newly_followed": true, "account_deleted": false}], "jumang4423_1726298192_jumang4423_1726146160": [{"id": "yoshihiko373", "unfollowed": false, "newly_followed": true, "account_deleted": false}, {"id": "amsw", "unfollowed": false, "newly_followed": true, "account_deleted": false}, {"id": "nivian-430520911", "unfollowed": false, "newly_followed": true, "account_deleted": false}, {"id": "starw3yy", "unfollowed": false, "newly_followed": true, "account_deleted": false}, {"id": "tobinosumire", "unfollowed": false, "newly_followed": true, "account_deleted": false}, {"id": "kn-zee", "unfollowed": false, "newly_followed": true, "account_deleted": false}, {"id": "pluggbient", "unfollowed": false, "newly_followed": false, "account_deleted": true}, {"id": "whyawe", "unfollowed": true, "newly_followed": false, "account_deleted": false}, {"id": "plsdonate333", "unfollowed": false, "newly_followed": false, "account_deleted": true}, {"id": "hdbn2", "unfollowed": true, "newly_followed": false, "account_deleted": false}, {"id": "deluxe-fantasy", "unfollowed": false, "newly_followed": false, "account_deleted": true}], "jumang4423_1726299737_jumang4423_1726298192": [{"id": "amsw", "unfollowed": true, "newly_followed": false, "account_deleted": false}], "jumang4423_1726542988_jumang4423_1726299737": [{"id": "taka-130236266", "unfollowed": false, "newly_followed": true, "account_deleted": false}, {"id": "mama9229", "unfollowed": false, "newly_followed": true, "account_deleted": false}, {"id": "4toku", "unfollowed": false, "newly_followed": true, "account_deleted": false}, {"id": "whyawe", "unfollowed": false, "newly_followed": true, "account_deleted": false}, {"id": "hdbn2", "unfollowed": false, "newly_followed": true, "account_deleted": false}, {"id": "ogi43", "unfollowed": false, "newly_followed": true, "account_deleted": false}, {"id": "yoshihiko373", "unfollowed": true, "newly_followed": false, "account_deleted": false}, {"id": "thoroughlyrelaxed", "unfollowed": false, "newly_followed": false, "account_deleted": true}, {"id": "uukhnyiaimbx", "unfollowed": false, "newly_followed": false, "account_deleted": true}], "jumang4423_1728038556_jumang4423_1726542988": [{"id": "user-390288657-87229230", "unfollowed": false, "newly_followed": true, "account_deleted": false}, {"id": "sileooo", "unfollowed": false, "newly_followed": true, "account_deleted": false}, {"id": "sango_nenza", "unfollowed": false, "newly_followed": true, "account_deleted": false}, {"id": "nassory", "unfollowed": false, "newly_followed": true, "account_deleted": false}, {"id": "atdjpta", "unfollowed": false, "newly_followed": true, "account_deleted": false}, {"id": "vaypy0szdstu", "unfollowed": false, "newly_followed": true, "account_deleted": false}, {"id": "k4nza5hift", "unfollowed": false, "newly_followed": true, "account_deleted": false}, {"id": "moeotak", "unfollowed": false, "newly_followed": true, "account_deleted": false}, {"id": "1i2ne1u", "unfollowed": false, "newly_followed": true, "account_deleted": false}, {"id": "leisha343", "unfollowed": false, "newly_followed": true, "account_deleted": false}, {"id": "omaijeee", "unfollowed": false, "newly_followed": true, "account_deleted": false}, {"id": "s-s-160453450", "unfollowed": false, "newly_followed": true, "account_deleted": false}, {"id": "cangurona", "unfollowed": false, "newly_followed": true, "account_deleted": false}, {"id": "aftglw", "unfollowed": false, "newly_followed": true, "account_deleted": false}, {"id": "prodvil", "unfollowed": false, "newly_followed": true, "account_deleted": false}, {"id": "usagi_morimori", "unfollowed": false, "newly_followed": true, "account_deleted": false}, {"id": "b0bbys1lva", "unfollowed": false, "newly_followed": true, "account_deleted": false}, {"id": "plugggbient", "unfollowed": false, "newly_followed": true, "account_deleted": false}, {"id": "qq_23", "unfollowed": false, "newly_followed": true, "account_deleted": false}, {"id": "shotaro-hirano-256287898", "unfollowed": false, "newly_followed": true, "account_deleted": false}, {"id": "punkimage", "unfollowed": false, "newly_followed": true, "account_deleted": false}, {"id": "21e8", "unfollowed": false, "newly_followed": true, "account_deleted": false}, {"id": "0den", "unfollowed": false, "newly_followed": true, "account_deleted": false}, {"id": "no1luvsu", "unfollowed": false, "newly_followed": true, "account_deleted": false}, {"id": "autohemophagia", "unfollowed": false, "newly_followed": true, "account_deleted": false}, {"id": "otaclave", "unfollowed": false, "newly_followed": true, "account_deleted": false}, {"id": "s7uuuxzxccsc", "unfollowed": false, "newly_followed": true, "account_deleted": false}, {"id": "mechanist1337", "unfollowed": false, "newly_followed": true, "account_deleted": false}, {"id": "sakumi-807952926", "unfollowed": false, "newly_followed": true, "account_deleted": false}, {"id": "4bc-rat", "unfollowed": false, "newly_followed": true, "account_deleted": false}, {"id": "5abmcp", "unfollowed": false, "newly_followed": true, "account_deleted": false}, {"id": "riedelchristoff", "unfollowed": false, "newly_followed": true, "account_deleted": false}, {"id": "lilbeshramko", "unfollowed": false, "newly_followed": true, "account_deleted": false}, {"id": "daskie666", "unfollowed": false, "newly_followed": true, "account_deleted": false}, {"id": "heoliene", "unfollowed": false, "newly_followed": true, "account_deleted": false}, {"id": "robopyro7", "unfollowed": false, "newly_followed": true, "account_deleted": false}, {"id": "tixsz", "unfollowed": false, "newly_followed": true, "account_deleted": false}, {"id": "jtc1", "unfollowed": false, "newly_followed": true, "account_deleted": false}, {"id": "gsmgsmgsm", "unfollowed": false, "newly_followed": true, "account_deleted": false}, {"id": "peepee_reason", "unfollowed": false, "newly_followed": true, "account_deleted": false}, {"id": "bashi80", "unfollowed": false, "newly_followed": true, "account_deleted": false}, {"id": "thisiscatastroph1c", "unfollowed": false, "newly_followed": true, "account_deleted": false}, {"id": "autolove", "unfollowed": false, "newly_followed": true, "account_deleted": false}, {"id": "violinbutterflynet", "unfollowed": false, "newly_followed": true, "account_deleted": false}, {"id": "ceruleanmei", "unfollowed": false, "newly_followed": true, "account_deleted": false}, {"id": "uukhnyiaimbx", "unfollowed": false, "newly_followed": true, "account_deleted": false}, {"id": "decryptids_danger_zone", "unfollowed": false, "newly_followed": true, "account_deleted": false}, {"id": "ver0l", "unfollowed": false, "newly_followed": true, "account_deleted": false}, {"id": "komarigyao", "unfollowed": false, "newly_followed": true, "account_deleted": false}, {"id": "jarldubz", "unfollowed": false, "newly_followed": true, "account_deleted": false}, {"id": "kn-zee", "unfollowed": false, "newly_followed": false, "account_deleted": true}, {"id": "qlxupwbaj1dm", "unfollowed": false, "newly_followed": false, "account_deleted": true}, {"id": "1mint", "unfollowed": true, "newly_followed": false, "account_deleted": false}, {"id": "viani-destello", "unfollowed": false, "newly_followed": false, "account_deleted": true}, {"id": "98465475", "unfollowed": false, "newly_followed": false, "account_deleted": true}, {"id": "birdybirdybirdymp3", "unfollowed": true, "newly_followed": false, "account_deleted": false}, {"id": "aeaiio", "unfollowed": false, "newly_followed": false, "account_deleted": true}, {"id": "presishigh", "unfollowed": false, "newly_followed": false, "account_deleted": true}, {"id": "schass", "unfollowed": false, "newly_followed": false, "account_deleted": true}, {"id": "isaacweloveyou", "unfollowed": false, "newly_followed": false, "account_deleted": true}, {"id": "raelorem", "unfollowed": false, "newly_followed": false, "account_deleted": true}, {"id": "57v", "unfollowed": false, "newly_followed": false, "account_deleted": true}, {"id": "10eo", "unfollowed": true, "newly_followed": false, "account_deleted": false}, {"id": "xnapzz", "unfollowed": false, "newly_followed": false, "account_deleted": true}, {"id": "karoocaloo", "unfollowed": true, "newly_followed": false, "account_deleted": false}, {"id": "c_c_sakura", "unfollowed": false, "newly_followed": false, "account_deleted": true}, {"id": "wateronthehill", "unfollowed": false, "newly_followed": false, "account_deleted": true}, {"id": "daxhuntlover", "unfollowed": false, "newly_followed": false, "account_deleted": true}, {"id": "nnnnooooouuuuu", "unfollowed": false, "newly_followed": false, "account_deleted": true}, {"id": "aaadv2775", "unfollowed": false, "newly_followed": false, "account_deleted": true}, {"id": "asidom7604", "unfollowed": false, "newly_followed": false, "account_deleted": true}], "jumang4423_1728836012_jumang4423_1728038556": [{"id": "soaptaker", "unfollowed": false, "newly_followed": true, "account_deleted": false}, {"id": "08313939", "unfollowed": false, "newly_followed": true, "account_deleted": false}, {"id": "faermeatangel", "unfollowed": false, "newly_followed": true, "account_deleted": false}, {"id": "irigino", "unfollowed": false, "newly_followed": true, "account_deleted": false}, {"id": "usdttrc20", "unfollowed": false, "newly_followed": true, "account_deleted": false}, {"id": "user-766895551", "unfollowed": false, "newly_followed": true, "account_deleted": false}, {"id": "47vxdmtgfuaj", "unfollowed": false, "newly_followed": true, "account_deleted": false}, {"id": "ha3r1n", "unfollowed": false, "newly_followed": true, "account_deleted": false}, {"id": "4urc", "unfollowed": false, "newly_followed": true, "account_deleted": false}, {"id": "qliclub", "unfollowed": false, "newly_followed": true, "account_deleted": false}, {"id": "yalikeit", "unfollowed": false, "newly_followed": true, "account_deleted": false}, {"id": "datakun69", "unfollowed": false, "newly_followed": true, "account_deleted": false}, {"id": "vyrestuff", "unfollowed": false, "newly_followed": true, "account_deleted": false}, {"id": "haveanaboveaverageday", "unfollowed": false, "newly_followed": true, "account_deleted": false}, {"id": "despidespi", "unfollowed": false, "newly_followed": true, "account_deleted": false}, {"id": "ssansssans", "unfollowed": false, "newly_followed": true, "account_deleted": false}, {"id": "dpn_jp", "unfollowed": false, "newly_followed": true, "account_deleted": false}, {"id": "plugggbient", "unfollowed": false, "newly_followed": false, "account_deleted": true}, {"id": "punkimage", "unfollowed": false, "newly_followed": false, "account_deleted": true}, {"id": "4toku", "unfollowed": true, "newly_followed": false, "account_deleted": false}, {"id": "yerin0821yerin", "unfollowed": true, "newly_followed": false, "account_deleted": false}, {"id": "tixsz", "unfollowed": false, "newly_followed": false, "account_deleted": true}, {"id": "satu01", "unfollowed": true, "newly_followed": false, "account_deleted": false}, {"id": "iloveallmydogs", "unfollowed": false, "newly_followed": false, "account_deleted": true}, {"id": "bashi80", "unfollowed": false, "newly_followed": false, "account_deleted": true}, {"id": "vaenis25", "unfollowed": false, "newly_followed": false, "account_deleted": true}, {"id": "autolove", "unfollowed": false, "newly_followed": false, "account_deleted": true}, {"id": "despirales", "unfollowed": false, "newly_followed": false, "account_deleted": true}, {"id": "rainsdeaf", "unfollowed": true, "newly_followed": false, "account_deleted": false}, {"id": "reffjey", "unfollowed": false, "newly_followed": false, "account_deleted": true}, {"id": "mocomaple", "unfollowed": false, "newly_followed": false, "account_deleted": true}], "jumang4423_1729601111_jumang4423_1728836012": [{"id": "2731046229", "unfollowed": false, "newly_followed": true, "account_deleted": false}, {"id": "hitsub", "unfollowed": false, "newly_followed": true, "account_deleted": false}, {"id": "loser4dim", "unfollowed": false, "newly_followed": true, "account_deleted": false}, {"id": "solavine", "unfollowed": false, "newly_followed": true, "account_deleted": false}, {"id": "lp7bygtqplhb", "unfollowed": false, "newly_followed": true, "account_deleted": false}, {"id": "hinatq", "unfollowed": false, "newly_followed": true, "account_deleted": false}, {"id": "user-429914294-133464451", "unfollowed": false, "newly_followed": true, "account_deleted": false}, {"id": "user-312578584", "unfollowed": false, "newly_followed": true, "account_deleted": false}, {"id": "nxpes", "unfollowed": false, "newly_followed": true, "account_deleted": false}, {"id": "t-boski", "unfollowed": false, "newly_followed": true, "account_deleted": false}, {"id": "fin-luis", "unfollowed": false, "newly_followed": true, "account_deleted": false}, {"id": "jng2354", "unfollowed": false, "newly_followed": true, "account_deleted": false}, {"id": "mirral", "unfollowed": false, "newly_followed": true, "account_deleted": false}, {"id": "captchame", "unfollowed": false, "newly_followed": true, "account_deleted": false}, {"id": "defconveteran", "unfollowed": false, "newly_followed": true, "account_deleted": false}, {"id": "kanyaeh", "unfollowed": false, "newly_followed": true, "account_deleted": false}, {"id": "vyrastuff", "unfollowed": false, "newly_followed": true, "account_deleted": false}, {"id": "sh1r4se", "unfollowed": false, "newly_followed": true, "account_deleted": false}, {"id": "soundpaintings", "unfollowed": false, "newly_followed": true, "account_deleted": false}, {"id": "krinaschannel", "unfollowed": false, "newly_followed": true, "account_deleted": false}, {"id": "cinemamurder", "unfollowed": false, "newly_followed": true, "account_deleted": false}, {"id": "ochimpokingdom", "unfollowed": false, "newly_followed": true, "account_deleted": false}, {"id": "user-390288657-87229230", "unfollowed": true, "newly_followed": false, "account_deleted": false}, {"id": "mechanist1337", "unfollowed": false, "newly_followed": false, "account_deleted": true}, {"id": "myakaibu", "unfollowed": false, "newly_followed": false, "account_deleted": true}, {"id": "user-2wm", "unfollowed": false, "newly_followed": false, "account_deleted": true}, {"id": "clown-toons", "unfollowed": false, "newly_followed": false, "account_deleted": true}, {"id": "vyrestuff", "unfollowed": false, "newly_followed": false, "account_deleted": true}, {"id": "t4t4ch1", "unfollowed": false, "newly_followed": false, "account_deleted": true}, {"id": "haveanaboveaverageday", "unfollowed": false, "newly_followed": false, "account_deleted": true}, {"id": "user-96047291", "unfollowed": false, "newly_followed": false, "account_deleted": true}, {"id": "kristian-naw", "unfollowed": false, "newly_followed": false, "account_deleted": true}, {"id": "vintre", "unfollowed": false, "newly_followed": false, "account_deleted": true}, {"id": "dpn_jp", "unfollowed": true, "newly_followed": false, "account_deleted": false}, {"id": "kzuha", "unfollowed": false, "newly_followed": false, "account_deleted": true}], "jumang4423_1730209397_jumang4423_1729601111": [{"id": "2vi2pdxlxdwx", "unfollowed": false, "newly_followed": true, "account_deleted": false}, {"id": "qfemc", "unfollowed": false, "newly_followed": true, "account_deleted": false}, {"id": "ludfurman", "unfollowed": false, "newly_followed": true, "account_deleted": false}, {"id": "pandalogia", "unfollowed": false, "newly_followed": true, "account_deleted": false}, {"id": "syava-the-kitchen", "unfollowed": false, "newly_followed": true, "account_deleted": false}, {"id": "yuki-777", "unfollowed": false, "newly_followed": true, "account_deleted": false}, {"id": "389p35byu89e5hmu", "unfollowed": false, "newly_followed": true, "account_deleted": false}, {"id": "b9gmtvxcvb8l", "unfollowed": false, "newly_followed": true, "account_deleted": false}, {"id": "dimalamperd", "unfollowed": false, "newly_followed": true, "account_deleted": false}, {"id": "contactdevide1", "unfollowed": false, "newly_followed": true, "account_deleted": false}, {"id": "yelvei", "unfollowed": false, "newly_followed": true, "account_deleted": false}, {"id": "fn4vf0rl9vku", "unfollowed": false, "newly_followed": true, "account_deleted": false}, {"id": "kirinwetfurs", "unfollowed": false, "newly_followed": true, "account_deleted": false}, {"id": "mikomik0", "unfollowed": false, "newly_followed": true, "account_deleted": false}, {"id": "madigamer123", "unfollowed": false, "newly_followed": true, "account_deleted": false}, {"id": "kilsksk", "unfollowed": false, "newly_followed": true, "account_deleted": false}, {"id": "uniwalier", "unfollowed": true, "newly_followed": false, "account_deleted": false}, {"id": "gravelmold", "unfollowed": false, "newly_followed": false, "account_deleted": true}], "jumang4423_1730383328_jumang4423_1730209397": [{"id": "stellar-dendrites1", "unfollowed": false, "newly_followed": true, "account_deleted": false}, {"id": "theoryofrelativity", "unfollowed": false, "newly_followed": true, "account_deleted": false}, {"id": "nrcid7f78u07", "unfollowed": false, "newly_followed": true, "account_deleted": false}, {"id": "pluggggbient", "unfollowed": false, "newly_followed": true, "account_deleted": false}, {"id": "windows11_23h2", "unfollowed": false, "newly_followed": true, "account_deleted": false}, {"id": "suteee", "unfollowed": false, "newly_followed": true, "account_deleted": false}, {"id": "2731046229", "unfollowed": false, "newly_followed": false, "account_deleted": true}, {"id": "mirral", "unfollowed": false, "newly_followed": false, "account_deleted": true}, {"id": "et-su-ko", "unfollowed": false, "newly_followed": false, "account_deleted": true}], "jumang4423_1730384169_jumang4423_1730383328": [], "jumang4423_1730839047_jumang4423_1730384169": [{"id": "128kzr", "unfollowed": false, "newly_followed": true, "account_deleted": false}, {"id": "cmqxtqniev6i", "unfollowed": false, "newly_followed": true, "account_deleted": false}, {"id": "dhodmjdm3458", "unfollowed": false, "newly_followed": true, "account_deleted": false}, {"id": "marija-685079110", "unfollowed": false, "newly_followed": true, "account_deleted": false}, {"id": "tokyomentale", "unfollowed": false, "newly_followed": true, "account_deleted": false}, {"id": "konrad-ekko", "unfollowed": false, "newly_followed": true, "account_deleted": false}, {"id": "user-715332245", "unfollowed": false, "newly_followed": true, "account_deleted": false}, {"id": "40kl", "unfollowed": false, "newly_followed": true, "account_deleted": false}, {"id": "krzysztofpikes", "unfollowed": false, "newly_followed": true, "account_deleted": false}, {"id": "metastable-void", "unfollowed": false, "newly_followed": true, "account_deleted": false}, {"id": "manonox", "unfollowed": false, "newly_followed": true, "account_deleted": false}, {"id": "2715990417", "unfollowed": false, "newly_followed": true, "account_deleted": false}, {"id": "hr13i", "unfollowed": false, "newly_followed": true, "account_deleted": false}, {"id": "iloveallmydogs", "unfollowed": false, "newly_followed": true, "account_deleted": false}, {"id": "schass", "unfollowed": false, "newly_followed": true, "account_deleted": false}, {"id": "starvvv", "unfollowed": false, "newly_followed": true, "account_deleted": false}, {"id": "djgoldenretriever", "unfollowed": false, "newly_followed": true, "account_deleted": false}, {"id": "pluggggbient", "unfollowed": false, "newly_followed": false, "account_deleted": true}, {"id": "satellite-686722453", "unfollowed": false, "newly_followed": false, "account_deleted": true}, {"id": "yalikeit", "unfollowed": false, "newly_followed": false, "account_deleted": true}, {"id": "datakun69", "unfollowed": false, "newly_followed": false, "account_deleted": true}, {"id": "starvvvv", "unfollowed": false, "newly_followed": false, "account_deleted": true}, {"id": "zaconline", "unfollowed": false, "newly_followed": false, "account_deleted": true}, {"id": "user-347381115", "unfollowed": false, "newly_followed": false, "account_deleted": true}, {"id": "zzoos", "unfollowed": true, "newly_followed": false, "account_deleted": false}, {"id": "snitchbitchesidontlike", "unfollowed": true, "newly_followed": false, "account_deleted": false}], "jumang4423_1734538030_jumang4423_1730839047": [{"id": "user-565981486", "unfollowed": false, "newly_followed": true, "account_deleted": false}, {"id": "kurog-kkrg", "unfollowed": false, "newly_followed": true, "account_deleted": false}, {"id": "purr-egg", "unfollowed": false, "newly_followed": true, "account_deleted": false}, {"id": "yidata", "unfollowed": false, "newly_followed": true, "account_deleted": false}, {"id": "lhklhklhk", "unfollowed": false, "newly_followed": true, "account_deleted": false}, {"id": "dotnet8", "unfollowed": false, "newly_followed": true, "account_deleted": false}, {"id": "julodose", "unfollowed": false, "newly_followed": true, "account_deleted": false}, {"id": "leotrixofficial", "unfollowed": false, "newly_followed": true, "account_deleted": false}, {"id": "deejay_girlfriend", "unfollowed": false, "newly_followed": true, "account_deleted": false}, {"id": "pa-ul-970987800", "unfollowed": false, "newly_followed": true, "account_deleted": false}, {"id": "user-128128128", "unfollowed": false, "newly_followed": true, "account_deleted": false}, {"id": "milliemaid", "unfollowed": false, "newly_followed": true, "account_deleted": false}, {"id": "seie", "unfollowed": false, "newly_followed": true, "account_deleted": false}, {"id": "heyitspixl", "unfollowed": false, "newly_followed": true, "account_deleted": false}, {"id": "oguro-shino", "unfollowed": false, "newly_followed": true, "account_deleted": false}, {"id": "kousuke-takaki-883219981", "unfollowed": false, "newly_followed": true, "account_deleted": false}, {"id": "llywelyn58", "unfollowed": false, "newly_followed": true, "account_deleted": false}, {"id": "yihvauv8ouj1", "unfollowed": false, "newly_followed": true, "account_deleted": false}, {"id": "tomboy_squirrel", "unfollowed": false, "newly_followed": true, "account_deleted": false}, {"id": "pqbfcpdechgp", "unfollowed": false, "newly_followed": true, "account_deleted": false}, {"id": "1lee-sc", "unfollowed": false, "newly_followed": true, "account_deleted": false}, {"id": "defn", "unfollowed": false, "newly_followed": true, "account_deleted": false}, {"id": "zzjay", "unfollowed": false, "newly_followed": true, "account_deleted": false}, {"id": "pyya", "unfollowed": false, "newly_followed": true, "account_deleted": false}, {"id": "omatzuri", "unfollowed": false, "newly_followed": true, "account_deleted": false}, {"id": "zuagbgnzlvl7", "unfollowed": false, "newly_followed": true, "account_deleted": false}, {"id": "891072", "unfollowed": false, "newly_followed": true, "account_deleted": false}, {"id": "killmystdubz", "unfollowed": false, "newly_followed": true, "account_deleted": false}, {"id": "daan-862862273", "unfollowed": false, "newly_followed": true, "account_deleted": false}, {"id": "darlin6fx", "unfollowed": false, "newly_followed": true, "account_deleted": false}, {"id": "hgb2201", "unfollowed": false, "newly_followed": true, "account_deleted": false}, {"id": "0-tomo-0", "unfollowed": false, "newly_followed": true, "account_deleted": false}, {"id": "t6pixt5p9rb6", "unfollowed": false, "newly_followed": true, "account_deleted": false}, {"id": "noel-riot", "unfollowed": false, "newly_followed": true, "account_deleted": false}, {"id": "novvicloud", "unfollowed": false, "newly_followed": true, "account_deleted": false}, {"id": "guy-laborde", "unfollowed": false, "newly_followed": true, "account_deleted": false}, {"id": "yuya-91911712", "unfollowed": false, "newly_followed": true, "account_deleted": false}, {"id": "timtim-722153751", "unfollowed": false, "newly_followed": true, "account_deleted": false}, {"id": "marco-rios-118579482", "unfollowed": false, "newly_followed": true, "account_deleted": false}, {"id": "shimon-41431731", "unfollowed": false, "newly_followed": true, "account_deleted": false}, {"id": "0ulqul", "unfollowed": false, "newly_followed": true, "account_deleted": false}, {"id": "zby988", "unfollowed": false, "newly_followed": true, "account_deleted": false}, {"id": "mekakure", "unfollowed": false, "newly_followed": true, "account_deleted": false}, {"id": "mo_e_mu", "unfollowed": false, "newly_followed": true, "account_deleted": false}, {"id": "paula-markkanen-620513784", "unfollowed": false, "newly_followed": true, "account_deleted": false}, {"id": "o4yckovoxwww", "unfollowed": false, "newly_followed": true, "account_deleted": false}, {"id": "koszmar", "unfollowed": false, "newly_followed": true, "account_deleted": false}, {"id": "sweater-874119524", "unfollowed": false, "newly_followed": true, "account_deleted": false}, {"id": "four-on-the-floor-926928624", "unfollowed": false, "newly_followed": true, "account_deleted": false}, {"id": "einedzan", "unfollowed": false, "newly_followed": true, "account_deleted": false}, {"id": "jeffverellen", "unfollowed": false, "newly_followed": true, "account_deleted": false}, {"id": "user-104097110", "unfollowed": false, "newly_followed": true, "account_deleted": false}, {"id": "francesco-de-gallo", "unfollowed": false, "newly_followed": true, "account_deleted": false}, {"id": "t-t-625227639", "unfollowed": false, "newly_followed": true, "account_deleted": false}, {"id": "mxdtse0fwqrr", "unfollowed": false, "newly_followed": true, "account_deleted": false}, {"id": "ofderi-debrief", "unfollowed": false, "newly_followed": true, "account_deleted": false}, {"id": "uruuew", "unfollowed": false, "newly_followed": true, "account_deleted": false}, {"id": "svqarmta4uj6", "unfollowed": false, "newly_followed": true, "account_deleted": false}, {"id": "dalup-delap", "unfollowed": false, "newly_followed": true, "account_deleted": false}, {"id": "qooldasai", "unfollowed": false, "newly_followed": true, "account_deleted": false}, {"id": "odoruhikikomori", "unfollowed": false, "newly_followed": true, "account_deleted": false}, {"id": "smox-xxx", "unfollowed": false, "newly_followed": true, "account_deleted": false}, {"id": "kobaii666", "unfollowed": false, "newly_followed": true, "account_deleted": false}, {"id": "pluggbnt", "unfollowed": false, "newly_followed": true, "account_deleted": false}, {"id": "nighcetis", "unfollowed": false, "newly_followed": true, "account_deleted": false}, {"id": "roseara", "unfollowed": false, "newly_followed": true, "account_deleted": false}, {"id": "frmyy", "unfollowed": false, "newly_followed": true, "account_deleted": false}, {"id": "nonoka07080000", "unfollowed": false, "newly_followed": true, "account_deleted": false}, {"id": "estisnothere", "unfollowed": false, "newly_followed": true, "account_deleted": false}, {"id": "captcha_captcha", "unfollowed": false, "newly_followed": true, "account_deleted": false}, {"id": "gmodravemix", "unfollowed": false, "newly_followed": true, "account_deleted": false}, {"id": "r4hcnes", "unfollowed": false, "newly_followed": true, "account_deleted": false}, {"id": "nlbi", "unfollowed": false, "newly_followed": true, "account_deleted": false}, {"id": "nicofreqs", "unfollowed": false, "newly_followed": true, "account_deleted": false}, {"id": "medichouse", "unfollowed": false, "newly_followed": true, "account_deleted": false}, {"id": "lowerlow", "unfollowed": false, "newly_followed": true, "account_deleted": false}, {"id": "kodaifukudakun", "unfollowed": false, "newly_followed": true, "account_deleted": false}, {"id": "despirales", "unfollowed": false, "newly_followed": true, "account_deleted": false}, {"id": "reffjey", "unfollowed": false, "newly_followed": true, "account_deleted": false}, {"id": "wolfiei", "unfollowed": false, "newly_followed": true, "account_deleted": false}, {"id": "cmqxtqniev6i", "unfollowed": false, "newly_followed": false, "account_deleted": true}, {"id": "dhodmjdm3458", "unfollowed": false, "newly_followed": false, "account_deleted": true}, {"id": "tokyomentale", "unfollowed": true, "newly_followed": false, "account_deleted": false}, {"id": "user-715332245", "unfollowed": false, "newly_followed": false, "account_deleted": true}, {"id": "krzysztofpikes", "unfollowed": true, "newly_followed": false, "account_deleted": false}, {"id": "kirinwetfurs", "unfollowed": true, "newly_followed": false, "account_deleted": false}, {"id": "madigamer123", "unfollowed": false, "newly_followed": false, "account_deleted": true}, {"id": "2715990417", "unfollowed": false, "newly_followed": false, "account_deleted": true}, {"id": "nivian-430520911", "unfollowed": false, "newly_followed": false, "account_deleted": true}, {"id": "user-802728012", "unfollowed": true, "newly_followed": false, "account_deleted": false}, {"id": "1roseara", "unfollowed": false, "newly_followed": false, "account_deleted": true}, {"id": "vuvuvuvu", "unfollowed": false, "newly_followed": false, "account_deleted": true}, {"id": "nonokaaaaaaa0708", "unfollowed": false, "newly_followed": false, "account_deleted": true}, {"id": "esther-man-1", "unfollowed": false, "newly_followed": false, "account_deleted": true}, {"id": "captchame", "unfollowed": false, "newly_followed": false, "account_deleted": true}, {"id": "ogi43", "unfollowed": false, "newly_followed": false, "account_deleted": true}, {"id": "sench4r", "unfollowed": true, "newly_followed": false, "account_deleted": false}, {"id": "zcx-wsx", "unfollowed": false, "newly_followed": false, "account_deleted": true}, {"id": "email_erotica", "unfollowed": false, "newly_followed": false, "account_deleted": true}, {"id": "defconveteran", "unfollowed": false, "newly_followed": false, "account_deleted": true}, {"id": "ethloc", "unfollowed": false, "newly_followed": false, "account_deleted": true}, {"id": "b0tw", "unfollowed": true, "newly_followed": false, "account_deleted": false}, {"id": "zrmqzi6r8i8j", "unfollowed": false, "newly_followed": false, "account_deleted": true}, {"id": "despidespi", "unfollowed": false, "newly_followed": false, "account_deleted": true}, {"id": "user-345518860", "unfollowed": true, "newly_followed": false, "account_deleted": false}, {"id": "silver_tears", "unfollowed": false, "newly_followed": false, "account_deleted": true}, {"id": "ssansssans", "unfollowed": false, "newly_followed": false, "account_deleted": true}, {"id": "mycatlarry", "unfollowed": false, "newly_followed": false, "account_deleted": true}, {"id": "animcloud70xx", "unfollowed": false, "newly_followed": false, "account_deleted": true}, {"id": "millz-muzic6342", "unfollowed": false, "newly_followed": false, "account_deleted": true}, {"id": "iamfoubs5879", "unfollowed": false, "newly_followed": false, "account_deleted": true}, {"id": "user-5160951533556", "unfollowed": false, "newly_followed": false, "account_deleted": true}, {"id": "estellia-idris6305", "unfollowed": false, "newly_followed": false, "account_deleted": true}, {"id": "connerkipbrandner", "unfollowed": false, "newly_followed": false, "account_deleted": true}, {"id": "yourmanhobs7052", "unfollowed": false, "newly_followed": false, "account_deleted": true}, {"id": "angela-6743053318736", "unfollowed": false, "newly_followed": false, "account_deleted": true}, {"id": "dick-fuckner4061", "unfollowed": false, "newly_followed": false, "account_deleted": true}, {"id": "cuzcooks9705965", "unfollowed": false, "newly_followed": false, "account_deleted": true}, {"id": "dopeybeatz6273", "unfollowed": false, "newly_followed": false, "account_deleted": true}, {"id": "alanbrendanlehman5", "unfollowed": false, "newly_followed": false, "account_deleted": true}, {"id": "jnny929580", "unfollowed": false, "newly_followed": false, "account_deleted": true}, {"id": "clutch_kid1984", "unfollowed": false, "newly_followed": false, "account_deleted": true}, {"id": "skkkkrrrt_mcgurt5834", "unfollowed": false, "newly_followed": false, "account_deleted": true}, {"id": "nicswelson5822", "unfollowed": false, "newly_followed": false, "account_deleted": true}, {"id": "user-8564484791994", "unfollowed": false, "newly_followed": false, "account_deleted": true}, {"id": "julia-gehrmann5159", "unfollowed": false, "newly_followed": false, "account_deleted": true}, {"id": "banjodownlow5678", "unfollowed": false, "newly_followed": false, "account_deleted": true}, {"id": "user-1421034588072", "unfollowed": false, "newly_followed": false, "account_deleted": true}, {"id": "jviindtricks5466", "unfollowed": false, "newly_followed": false, "account_deleted": true}, {"id": "avery-camacho-4922155557062", "unfollowed": false, "newly_followed": false, "account_deleted": true}, {"id": "julian-david-dixon6848", "unfollowed": false, "newly_followed": false, "account_deleted": true}, {"id": "3vilsxd5585", "unfollowed": false, "newly_followed": false, "account_deleted": true}, {"id": "allysianga3795", "unfollowed": false, "newly_followed": false, "account_deleted": true}, {"id": "jairdelgado5909", "unfollowed": false, "newly_followed": false, "account_deleted": true}, {"id": "adrian-asuncion-31119", "unfollowed": false, "newly_followed": false, "account_deleted": true}, {"id": "jordan-drake6765", "unfollowed": false, "newly_followed": false, "account_deleted": true}, {"id": "george-manson-6360012397367", "unfollowed": false, "newly_followed": false, "account_deleted": true}, {"id": "james-wieland3923", "unfollowed": false, "newly_followed": false, "account_deleted": true}, {"id": "babygl0w5549", "unfollowed": false, "newly_followed": false, "account_deleted": true}, {"id": "conartistprods3534", "unfollowed": false, "newly_followed": false, "account_deleted": true}, {"id": "anastasia-tatarchuk-1156245979586", "unfollowed": false, "newly_followed": false, "account_deleted": true}, {"id": "pedro-cabral-312461", "unfollowed": false, "newly_followed": false, "account_deleted": true}, {"id": "aya_music7828", "unfollowed": false, "newly_followed": false, "account_deleted": true}, {"id": "jackson-morrison-25116", "unfollowed": false, "newly_followed": false, "account_deleted": true}, {"id": "jedi_marzan4847", "unfollowed": false, "newly_followed": false, "account_deleted": true}, {"id": "goldenbender7383", "unfollowed": false, "newly_followed": false, "account_deleted": true}, {"id": "corbdorb6212", "unfollowed": false, "newly_followed": false, "account_deleted": true}, {"id": "daniel-liu-486515", "unfollowed": false, "newly_followed": false, "account_deleted": true}, {"id": "josue-ramirez-5032775157456", "unfollowed": false, "newly_followed": false, "account_deleted": true}, {"id": "laymetorest5956", "unfollowed": false, "newly_followed": false, "account_deleted": true}, {"id": "joshwuhh4862", "unfollowed": false, "newly_followed": false, "account_deleted": true}, {"id": "aryasharma2846", "unfollowed": false, "newly_followed": false, "account_deleted": true}, {"id": "bruxaozera8743", "unfollowed": false, "newly_followed": false, "account_deleted": true}, {"id": "jfns4875", "unfollowed": false, "newly_followed": false, "account_deleted": true}, {"id": "hilton-docking1030", "unfollowed": false, "newly_followed": false, "account_deleted": true}, {"id": "garylancegibbs1975", "unfollowed": false, "newly_followed": false, "account_deleted": true}, {"id": "hurryk1884", "unfollowed": false, "newly_followed": false, "account_deleted": true}, {"id": "hbk0729741", "unfollowed": false, "newly_followed": false, "account_deleted": true}, {"id": "hiimendeavor4016", "unfollowed": false, "newly_followed": false, "account_deleted": true}, {"id": "imdownsy6297", "unfollowed": false, "newly_followed": false, "account_deleted": true}, {"id": "ianrimason", "unfollowed": false, "newly_followed": false, "account_deleted": true}, {"id": "heffyraps8756", "unfollowed": false, "newly_followed": false, "account_deleted": true}, {"id": "stfulilbih7282", "unfollowed": false, "newly_followed": false, "account_deleted": true}, {"id": "jonathan-zhang-88392", "unfollowed": false, "newly_followed": false, "account_deleted": true}, {"id": "drake-davis-125032", "unfollowed": false, "newly_followed": false, "account_deleted": true}, {"id": "domantas-gau-as6794", "unfollowed": false, "newly_followed": false, "account_deleted": true}, {"id": "evanbrockmcginn1", "unfollowed": false, "newly_followed": false, "account_deleted": true}, {"id": "nhats3398", "unfollowed": false, "newly_followed": false, "account_deleted": true}, {"id": "dj-b-eso4408", "unfollowed": false, "newly_followed": false, "account_deleted": true}, {"id": "errickkauckboi30001655", "unfollowed": false, "newly_followed": false, "account_deleted": true}, {"id": "dabbaranks7108674", "unfollowed": false, "newly_followed": false, "account_deleted": true}, {"id": "kennedywestwood2205", "unfollowed": false, "newly_followed": false, "account_deleted": true}, {"id": "jonny-hans7581", "unfollowed": false, "newly_followed": false, "account_deleted": true}, {"id": "nonstopbeatsamw2076", "unfollowed": false, "newly_followed": false, "account_deleted": true}, {"id": "iarek-pomigalov1232", "unfollowed": false, "newly_followed": false, "account_deleted": true}, {"id": "dam-da-1710396158130", "unfollowed": false, "newly_followed": false, "account_deleted": true}], "jumang4423_1734894746_jumang4423_1734538030": [{"id": "abbadonvr", "unfollowed": false, "newly_followed": true, "account_deleted": false}, {"id": "boneprotrusion", "unfollowed": false, "newly_followed": true, "account_deleted": false}, {"id": "clayton1013", "unfollowed": false, "newly_followed": true, "account_deleted": false}, {"id": "foyobro", "unfollowed": false, "newly_followed": true, "account_deleted": false}, {"id": "esiier", "unfollowed": false, "newly_followed": true, "account_deleted": false}, {"id": "psorvl", "unfollowed": false, "newly_followed": true, "account_deleted": false}, {"id": "faeble-online", "unfollowed": false, "newly_followed": true, "account_deleted": false}, {"id": "tapham", "unfollowed": false, "newly_followed": true, "account_deleted": false}, {"id": "kyomonemui", "unfollowed": false, "newly_followed": true, "account_deleted": false}, {"id": "beatsbybearcub", "unfollowed": false, "newly_followed": false, "account_deleted": true}, {"id": "tanthieugia2", "unfollowed": false, "newly_followed": false, "account_deleted": true}, {"id": "imaginexuan", "unfollowed": true, "newly_followed": false, "account_deleted": false}, {"id": "revo-liansyah", "unfollowed": false, "newly_followed": false, "account_deleted": true}], "jumang4423_1735217673_jumang4423_1734894746": [{"id": "axistwelve", "unfollowed": false, "newly_followed": true, "account_deleted": false}, {"id": "romi-107087720", "unfollowed": false, "newly_followed": true, "account_deleted": false}, {"id": "kisl-349624359", "unfollowed": false, "newly_followed": true, "account_deleted": false}, {"id": "weareoutlaw", "unfollowed": false, "newly_followed": true, "account_deleted": false}, {"id": "slowglow-425681113", "unfollowed": false, "newly_followed": true, "account_deleted": false}, {"id": "niko-jonard", "unfollowed": false, "newly_followed": true, "account_deleted": false}, {"id": "user-42050130", "unfollowed": false, "newly_followed": true, "account_deleted": false}, {"id": "public-route", "unfollowed": false, "newly_followed": true, "account_deleted": false}, {"id": "user-470095355-851721438", "unfollowed": false, "newly_followed": true, "account_deleted": false}, {"id": "jellypop666", "unfollowed": false, "newly_followed": true, "account_deleted": false}, {"id": "kaiba2008o", "unfollowed": false, "newly_followed": true, "account_deleted": false}, {"id": "2678", "unfollowed": false, "newly_followed": true, "account_deleted": false}, {"id": "esiier", "unfollowed": true, "newly_followed": false, "account_deleted": false}, {"id": "1lee-sc", "unfollowed": true, "newly_followed": false, "account_deleted": false}, {"id": "kobaii666", "unfollowed": false, "newly_followed": false, "account_deleted": true}, {"id": "yomin_yomin", "unfollowed": false, "newly_followed": false, "account_deleted": true}, {"id": "nxahj11", "unfollowed": true, "newly_followed": false, "account_deleted": false}, {"id": "novae267", "unfollowed": false, "newly_followed": false, "account_deleted": true}], "jumang4423_1735568111_jumang4423_1735217673": [{"id": "user-269139220", "unfollowed": false, "newly_followed": true, "account_deleted": false}, {"id": "nccs7kqdelv5", "unfollowed": false, "newly_followed": true, "account_deleted": false}, {"id": "vraigringo", "unfollowed": false, "newly_followed": true, "account_deleted": false}, {"id": "danielsousx", "unfollowed": false, "newly_followed": true, "account_deleted": false}, {"id": "user-624214168-479763308", "unfollowed": false, "newly_followed": true, "account_deleted": false}, {"id": "imnotasalmon", "unfollowed": false, "newly_followed": true, "account_deleted": false}, {"id": "pacificship-895", "unfollowed": false, "newly_followed": true, "account_deleted": false}, {"id": "gaszia", "unfollowed": false, "newly_followed": true, "account_deleted": false}, {"id": "johnmark-lopez", "unfollowed": false, "newly_followed": true, "account_deleted": false}, {"id": "cmcurry8", "unfollowed": false, "newly_followed": true, "account_deleted": false}, {"id": "nysyi", "unfollowed": false, "newly_followed": true, "account_deleted": false}, {"id": "saphimusics", "unfollowed": false, "newly_followed": true, "account_deleted": false}, {"id": "stephiemusic", "unfollowed": false, "newly_followed": true, "account_deleted": false}, {"id": "stutterparade", "unfollowed": false, "newly_followed": true, "account_deleted": false}, {"id": "angelrestante", "unfollowed": false, "newly_followed": true, "account_deleted": false}, {"id": "sneekiblin", "unfollowed": false, "newly_followed": true, "account_deleted": false}, {"id": "ddoy3nsyacai", "unfollowed": false, "newly_followed": true, "account_deleted": false}, {"id": "avo-k-846888726", "unfollowed": false, "newly_followed": true, "account_deleted": false}, {"id": "aallee1000000", "unfollowed": false, "newly_followed": true, "account_deleted": false}, {"id": "galaxity-647405377", "unfollowed": false, "newly_followed": true, "account_deleted": false}, {"id": "basilemusicsounds", "unfollowed": false, "newly_followed": true, "account_deleted": false}, {"id": "ethnoethno", "unfollowed": false, "newly_followed": true, "account_deleted": false}, {"id": "user-34928998", "unfollowed": false, "newly_followed": true, "account_deleted": false}, {"id": "tk-tk-161092514", "unfollowed": false, "newly_followed": true, "account_deleted": false}, {"id": "yoh-hitsujida-40hsh33p", "unfollowed": false, "newly_followed": true, "account_deleted": false}, {"id": "41php", "unfollowed": false, "newly_followed": true, "account_deleted": false}, {"id": "supermoto-1-761434382", "unfollowed": false, "newly_followed": true, "account_deleted": false}, {"id": "orczi96", "unfollowed": false, "newly_followed": true, "account_deleted": false}, {"id": "sophiaanalogg8888", "unfollowed": false, "newly_followed": true, "account_deleted": false}, {"id": "p_chicken", "unfollowed": false, "newly_followed": true, "account_deleted": false}, {"id": "vitalityorb", "unfollowed": false, "newly_followed": true, "account_deleted": false}, {"id": "youngdabiex", "unfollowed": false, "newly_followed": true, "account_deleted": false}, {"id": "koszmar", "unfollowed": false, "newly_followed": false, "account_deleted": true}, {"id": "odoruhikikomori", "unfollowed": true, "newly_followed": false, "account_deleted": false}, {"id": "jellypop666", "unfollowed": false, "newly_followed": false, "account_deleted": true}, {"id": "yung_ballsack", "unfollowed": false, "newly_followed": false, "account_deleted": true}, {"id": "skye2k", "unfollowed": false, "newly_followed": false, "account_deleted": true}, {"id": "itz_shy", "unfollowed": false, "newly_followed": false, "account_deleted": true}, {"id": "onrrne", "unfollowed": false, "newly_followed": false, "account_deleted": true}], "jumang4423_1735728451_jumang4423_1735568111": [{"id": "xiangyu-unfold", "unfollowed": false, "newly_followed": true, "account_deleted": false}, {"id": "yeheayh", "unfollowed": false, "newly_followed": true, "account_deleted": false}, {"id": "voxoku", "unfollowed": false, "newly_followed": true, "account_deleted": false}, {"id": "daniel-field-963880979", "unfollowed": false, "newly_followed": true, "account_deleted": false}, {"id": "starvingspirit", "unfollowed": false, "newly_followed": true, "account_deleted": false}, {"id": "joseph-toof", "unfollowed": false, "newly_followed": true, "account_deleted": false}, {"id": "dtevguhmtp6x", "unfollowed": false, "newly_followed": true, "account_deleted": false}, {"id": "gettinggirlscared", "unfollowed": false, "newly_followed": true, "account_deleted": false}, {"id": "user-156104444", "unfollowed": false, "newly_followed": true, "account_deleted": false}, {"id": "dntel", "unfollowed": false, "newly_followed": true, "account_deleted": false}, {"id": "shininghalo", "unfollowed": false, "newly_followed": true, "account_deleted": false}, {"id": "tielsie", "unfollowed": false, "newly_followed": true, "account_deleted": false}, {"id": "bbb01100010", "unfollowed": false, "newly_followed": true, "account_deleted": false}, {"id": "oakscreen", "unfollowed": false, "newly_followed": true, "account_deleted": false}, {"id": "louis-l-c-861085700", "unfollowed": false, "newly_followed": true, "account_deleted": false}, {"id": "pluggbnt-72473", "unfollowed": false, "newly_followed": true, "account_deleted": false}, {"id": "slowglow-425681113", "unfollowed": true, "newly_followed": false, "account_deleted": false}, {"id": "pluggbnt", "unfollowed": false, "newly_followed": false, "account_deleted": true}], "jumang4423_1730384169_jumang4423_1730209397": [{"id": "stellar-dendrites1", "unfollowed": false, "newly_followed": true, "account_deleted": false}, {"id": "theoryofrelativity", "unfollowed": false, "newly_followed": true, "account_deleted": false}, {"id": "nrcid7f78u07", "unfollowed": false, "newly_followed": true, "account_deleted": false}, {"id": "pluggggbient", "unfollowed": false, "newly_followed": true, "account_deleted": false}, {"id": "windows11_23h2", "unfollowed": false, "newly_followed": true, "account_deleted": false}, {"id": "suteee", "unfollowed": false, "newly_followed": true, "account_deleted": false}, {"id": "2731046229", "unfollowed": false, "newly_followed": false, "account_deleted": true}, {"id": "mirral", "unfollowed": false, "newly_followed": false, "account_deleted": true}, {"id": "et-su-ko", "unfollowed": false, "newly_followed": false, "account_deleted": true}], "jumang4423_1735749718_jumang4423_1735728451": [], "jumang4423_1735750421_jumang4423_1735749718": []}